[
  {
    "links": [],
    "meta": {
      "time": 1533632845799,
      "source": {
        "domainId": "example.domain"
      },
      "id": "2d9b365e-9c1a-4075-87f2-a8c630e86f87",
      "type": "EiffelSourceChangeSubmittedEvent",
      "version": "1.0.0"
    },
    "data": {
      "gitIdentifier": {
        "repoName": "myRepo",
        "branch": "master",
        "repoUri": "https://repo.com",
        "commitId": "fd090b60a4aedc5161da9c035a49b14a319829b4"
      },
      "customData": [
        {
          "key": "name",
          "value": "SCS1"
        },
        {
          "key": "iteration",
          "value": 0
        }
      ],
      "submitter": {
        "email": "john.doe@company.com",
        "id": "johnxxx",
        "group": "Team Gophers",
        "name": "John Doe"
      }
    }
  },
  {
    "links": [],
    "meta": {
      "time": 1533632845800,
      "source": {
        "domainId": "example.domain"
      },
      "id": "38c7d1d5-3f62-4932-94a7-f7be7b5200e6",
      "type": "EiffelEnvironmentDefinedEvent",
      "version": "1.0.0"
    },
    "data": {
      "customData": [
        {
          "key": "name",
          "value": "EDef1"
        },
        {
          "key": "iteration",
          "value": 0
        }
      ],
      "name": "Environment 1",
      "version": "0"
    }
  },
  {
    "links": [],
    "meta": {
      "time": 1533632845801,
      "source": {
        "domainId": "example.domain"
      },
      "id": "e0b5e701-6f6a-4a11-bdb2-b7f487497a27",
      "type": "EiffelEnvironmentDefinedEvent",
      "version": "1.0.0"
    },
    "data": {
      "customData": [
        {
          "key": "name",
          "value": "EDef2"
        },
        {
          "key": "iteration",
          "value": 0
        }
      ],
      "name": "Environment 2",
      "version": "0"
    }
  },
  {
    "links": [],
    "meta": {
      "time": 1533632845802,
      "source": {
        "domainId": "example.domain"
      },
      "id": "a3a48338-35c7-426b-9cc3-42ffbf19881c",
      "type": "EiffelArtifactCreatedEvent",
      "version": "2.0.0"
    },
    "data": {
      "customData": [
        {
          "key": "name",
          "value": "ArtC3"
        },
        {
          "key": "iteration",
          "value": 0
        }
      ],
      "identity": "pkg:maven/com.othercompany.library/third-party-library@3.2.4"
    }
  },
  {
    "links": [
      {
        "target": "2d9b365e-9c1a-4075-87f2-a8c630e86f87",
        "type": "ELEMENT"
      }
    ],
    "meta": {
      "time": 1533632845803,
      "source": {
        "domainId": "example.domain"
      },
      "id": "d57b9a7a-3fae-4c3e-b065-b9bf1ad5ba0d",
      "type": "EiffelCompositionDefinedEvent",
      "version": "1.0.0"
    },
    "data": {
      "customData": [
        {
          "key": "name",
          "value": "CDef3"
        },
        {
          "key": "iteration",
          "value": 0
        }
      ],
      "name": "Composition 3",
      "version": "0"
    }
  },
  {
    "links": [
      {
        "target": "d57b9a7a-3fae-4c3e-b065-b9bf1ad5ba0d",
        "type": "COMPOSITION"
      },
      {
        "target": "d57b9a7a-3fae-4c3e-b065-b9bf1ad5ba0d",
        "type": "CAUSE"
      }
    ],
    "meta": {
      "time": 1533632845804,
      "source": {
        "domainId": "example.domain"
      },
      "id": "8fb3721f-18ad-447e-9527-4c82a8853beb",
      "type": "EiffelArtifactCreatedEvent",
      "version": "2.0.0"
    },
    "data": {
      "customData": [
        {
          "key": "name",
          "value": "ArtCC1"
        },
        {
          "key": "iteration",
          "value": 0
        }
      ],
      "identity": "pkg:maven/com.mycompany.myproduct/component-1@1.0.0"
    }
  },
  {
    "links": [
      {
        "target": "d57b9a7a-3fae-4c3e-b065-b9bf1ad5ba0d",
        "type": "COMPOSITION"
      },
      {
        "target": "d57b9a7a-3fae-4c3e-b065-b9bf1ad5ba0d",
        "type": "CAUSE"
      }
    ],
    "meta": {
      "time": 1533632845805,
      "source": {
        "domainId": "example.domain"
      },
      "id": "9893af82-d7e1-4942-9d1d-5f6a741ac13d",
      "type": "EiffelArtifactCreatedEvent",
      "version": "2.0.0"
    },
    "data": {
      "customData": [
        {
          "key": "name",
          "value": "ArtCC2"
        },
        {
          "key": "iteration",
          "value": 0
        }
      ],
      "identity": "pkg:maven/com.mycompany.myproduct/component-2@1.0.0"
    }
  },
  {
    "links": [
      {
        "target": "d57b9a7a-3fae-4c3e-b065-b9bf1ad5ba0d",
        "type": "COMPOSITION"
      },
      {
        "target": "d57b9a7a-3fae-4c3e-b065-b9bf1ad5ba0d",
        "type": "CAUSE"
      }
    ],
    "meta": {
      "time": 1533632845806,
      "source": {
        "domainId": "example.domain"
      },
      "id": "7e36245b-4ed5-4770-84f7-2213f91f748a",
      "type": "EiffelArtifactCreatedEvent",
      "version": "2.0.0"
    },
    "data": {
      "customData": [
        {
          "key": "name",
          "value": "ArtCC3"
        },
        {
          "key": "iteration",
          "value": 0
        }
      ],
      "identity": "pkg:maven/com.mycompany.myproduct/component-3@1.0.0"
    }
  },
  {
    "links": [
      {
        "target": "2d9b365e-9c1a-4075-87f2-a8c630e86f87",
        "type": "BASE"
      }
    ],
    "meta": {
      "time": 1533632855807,
      "source": {
        "domainId": "example.domain"
      },
      "id": "743f74f7-9d36-4463-9210-289d56b44d2e",
      "type": "EiffelSourceChangeCreatedEvent",
      "version": "1.0.0"
    },
    "data": {
      "author": {
        "email": "john.doe@company.com",
        "id": "johnxxx",
        "group": "Team Gophers",
        "name": "John Doe"
      },
      "gitIdentifier": {
        "repoName": "myRepo",
        "branch": "topic-branch-1",
        "repoUri": "https://repo.com",
        "commitId": "fd090b60a4aedc5161da9c035a49b14a319829c5"
      },
      "customData": [
        {
          "key": "name",
          "value": "SCC1"
        },
        {
          "key": "iteration",
          "value": 1
        }
      ],
      "change": {
        "files": "https://filelist.com/1",
        "deletions": 130,
        "insertions": 48
      }
    }
  },
  {
    "links": [
      {
        "target": "2d9b365e-9c1a-4075-87f2-a8c630e86f87",
        "type": "PREVIOUS_VERSION"
      },
      {
        "target": "743f74f7-9d36-4463-9210-289d56b44d2e",
        "type": "CHANGE"
      }
    ],
    "meta": {
      "time": 1533632855808,
      "source": {
        "domainId": "example.domain"
      },
      "id": "40fe0f7e-7ee2-454a-8d1a-1b7a5e12bff7",
      "type": "EiffelSourceChangeSubmittedEvent",
      "version": "1.0.0"
    },
    "data": {
      "gitIdentifier": {
        "repoName": "myRepo",
        "branch": "master",
        "repoUri": "https://repo.com",
        "commitId": "fd090b60a4aedc5161da9c035a49b14a319829b4"
      },
      "customData": [
        {
          "key": "name",
          "value": "SCS1"
        },
        {
          "key": "iteration",
          "value": 1
        }
      ],
      "submitter": {
        "email": "john.doe@company.com",
        "id": "johnxxx",
        "group": "Team Gophers",
        "name": "John Doe"
      }
    }
  },
  {
    "links": [
      {
        "target": "d57b9a7a-3fae-4c3e-b065-b9bf1ad5ba0d",
        "type": "PREVIOUS_VERSION"
      },
      {
        "target": "40fe0f7e-7ee2-454a-8d1a-1b7a5e12bff7",
        "type": "ELEMENT"
      }
    ],
    "meta": {
      "time": 1533632855908,
      "source": {
        "domainId": "example.domain"
      },
      "id": "c9465287-b31d-4907-8129-6cead44bb2df",
      "type": "EiffelCompositionDefinedEvent",
      "version": "1.0.0"
    },
    "data": {
      "customData": [
        {
          "key": "name",
          "value": "CDef3"
        },
        {
          "key": "iteration",
          "value": 1
        }
      ],
      "name": "Composition 3",
      "version": "1"
    }
  },
  {
    "links": [
      {
        "target": "c9465287-b31d-4907-8129-6cead44bb2df",
        "type": "COMPOSITION"
      },
      {
        "target": "c9465287-b31d-4907-8129-6cead44bb2df",
        "type": "CAUSE"
      },
      {
        "target": "8fb3721f-18ad-447e-9527-4c82a8853beb",
        "type": "PREVIOUS_VERSION"
      }
    ],
    "meta": {
      "time": 1533633055908,
      "source": {
        "domainId": "example.domain"
      },
      "id": "bbfeee0a-68a9-450e-909c-3552cb490886",
      "type": "EiffelArtifactCreatedEvent",
      "version": "2.0.0"
    },
    "data": {
      "customData": [
        {
          "key": "name",
          "value": "ArtCC1"
        },
        {
          "key": "iteration",
          "value": 1
        }
      ],
      "identity": "pkg:maven/com.mycompany.myproduct/component-1@1.1.0"
    }
  },
  {
    "links": [
      {
        "target": "c9465287-b31d-4907-8129-6cead44bb2df",
        "type": "COMPOSITION"
      },
      {
        "target": "c9465287-b31d-4907-8129-6cead44bb2df",
        "type": "CAUSE"
      },
      {
        "target": "9893af82-d7e1-4942-9d1d-5f6a741ac13d",
        "type": "PREVIOUS_VERSION"
      }
    ],
    "meta": {
      "time": 1533633090908,
      "source": {
        "domainId": "example.domain"
      },
      "id": "33168379-f560-448f-92d1-2cab2c985e87",
      "type": "EiffelArtifactCreatedEvent",
      "version": "2.0.0"
    },
    "data": {
      "customData": [
        {
          "key": "name",
          "value": "ArtCC2"
        },
        {
          "key": "iteration",
          "value": 1
        }
      ],
      "identity": "pkg:maven/com.mycompany.myproduct/component-2@1.1.0"
    }
  },
  {
    "links": [
      {
        "target": "c9465287-b31d-4907-8129-6cead44bb2df",
        "type": "COMPOSITION"
      },
      {
        "target": "c9465287-b31d-4907-8129-6cead44bb2df",
        "type": "CAUSE"
      },
      {
        "target": "7e36245b-4ed5-4770-84f7-2213f91f748a",
        "type": "PREVIOUS_VERSION"
      }
    ],
    "meta": {
      "time": 1533633091908,
      "source": {
        "domainId": "example.domain"
      },
      "id": "5577c3e8-b207-49c1-b597-cbafe814633e",
      "type": "EiffelArtifactCreatedEvent",
      "version": "2.0.0"
    },
    "data": {
      "customData": [
        {
          "key": "name",
          "value": "ArtCC3"
        },
        {
          "key": "iteration",
          "value": 1
        }
      ],
      "identity": "pkg:maven/com.mycompany.myproduct/component-3@1.1.0"
    }
  },
  {
    "links": [
      {
        "target": "bbfeee0a-68a9-450e-909c-3552cb490886",
        "type": "CAUSE"
      },
      {
        "target": "33168379-f560-448f-92d1-2cab2c985e87",
        "type": "CAUSE"
      },
      {
        "target": "5577c3e8-b207-49c1-b597-cbafe814633e",
        "type": "CAUSE"
      }
    ],
    "meta": {
      "time": 1533633092008,
      "source": {
        "domainId": "example.domain"
      },
      "id": "89a935c3-f0ea-4909-991f-3b85121d45a4",
      "type": "EiffelActivityTriggeredEvent",
      "version": "1.0.0"
    },
    "data": {
      "triggers": [
        {
          "type": "EIFFEL_EVENT"
        }
      ],
      "customData": [
        {
          "key": "name",
          "value": "ActT4"
        },
        {
          "key": "iteration",
          "value": 1
        }
      ],
      "categories": [
        "Sub-system Build Activity"
      ],
      "executionType": "AUTOMATED",
      "name": "Act4"
    }
  },
  {
    "links": [
      {
        "target": "89a935c3-f0ea-4909-991f-3b85121d45a4",
        "type": "ACTIVITY_EXECUTION"
      }
    ],
    "meta": {
      "time": 1533633092009,
      "source": {
        "domainId": "example.domain"
      },
      "id": "72f35d6d-fb18-4268-b48b-eba6d4d9d982",
      "type": "EiffelActivityStartedEvent",
      "version": "1.0.0"
    },
    "data": {
      "customData": [
        {
          "key": "name",
          "value": "ActS4"
        },
        {
          "key": "iteration",
          "value": 1
        }
      ]
    }
  },
  {
    "links": [
      {
        "target": "89a935c3-f0ea-4909-991f-3b85121d45a4",
        "type": "CONTEXT"
      },
      {
        "target": "bbfeee0a-68a9-450e-909c-3552cb490886",
        "type": "ELEMENT"
      },
      {
        "target": "33168379-f560-448f-92d1-2cab2c985e87",
        "type": "ELEMENT"
      },
      {
        "target": "5577c3e8-b207-49c1-b597-cbafe814633e",
        "type": "ELEMENT"
      }
    ],
    "meta": {
      "time": 1533633092109,
      "source": {
        "domainId": "example.domain"
      },
      "id": "745e698f-f177-4e05-acdd-bb38f49198a1",
      "type": "EiffelCompositionDefinedEvent",
      "version": "1.0.0"
    },
    "data": {
      "customData": [
        {
          "key": "name",
          "value": "CDef2"
        },
        {
          "key": "iteration",
          "value": 1
        }
      ],
      "name": "Composition 2",
      "version": "1"
    }
  },
  {
    "links": [
      {
        "target": "745e698f-f177-4e05-acdd-bb38f49198a1",
        "type": "COMPOSITION"
      },
      {
        "target": "e0b5e701-6f6a-4a11-bdb2-b7f487497a27",
        "type": "ENVIRONMENT"
      },
      {
        "target": "89a935c3-f0ea-4909-991f-3b85121d45a4",
        "type": "CONTEXT"
      }
    ],
    "meta": {
      "time": 1533633092209,
      "source": {
        "domainId": "example.domain"
      },
      "id": "208cfc27-23f7-469d-a741-b15ac150bf8c",
      "type": "EiffelArtifactCreatedEvent",
      "version": "2.0.0"
    },
    "data": {
      "customData": [
        {
          "key": "name",
          "value": "ArtC2"
        },
        {
          "key": "iteration",
          "value": 1
        }
      ],
      "identity": "pkg:maven/com.mycompany.myproduct/sub-system@1.1.0"
    }
  },
  {
    "links": [
      {
        "target": "208cfc27-23f7-469d-a741-b15ac150bf8c",
        "type": "ARTIFACT"
      },
      {
        "target": "89a935c3-f0ea-4909-991f-3b85121d45a4",
        "type": "CONTEXT"
      }
    ],
    "meta": {
      "time": 1533633122209,
      "source": {
        "domainId": "example.domain"
      },
      "id": "3593b445-773a-469e-977f-0456e4224d1c",
      "type": "EiffelArtifactPublishedEvent",
      "version": "1.0.0"
    },
    "data": {
      "locations": [
        {
          "uri": "https://myrepository.com/mySubSystemArtifact",
          "type": "PLAIN"
        }
      ],
      "customData": [
        {
          "key": "name",
          "value": "ArtP2"
        },
        {
          "key": "iteration",
          "value": 1
        }
      ]
    }
  },
  {
    "links": [
      {
        "target": "89a935c3-f0ea-4909-991f-3b85121d45a4",
        "type": "ACTIVITY_EXECUTION"
      }
    ],
    "meta": {
      "time": 1533633122259,
      "source": {
        "domainId": "example.domain"
      },
      "id": "93fb8227-9b0e-4084-839b-07845df0b38c",
      "type": "EiffelActivityFinishedEvent",
      "version": "1.0.0"
    },
    "data": {
      "outcome": {
        "conclusion": "SUCCESSFUL"
      },
      "customData": [
        {
          "key": "name",
          "value": "ActF4"
        },
        {
          "key": "iteration",
          "value": 1
        }
      ]
    }
  },
  {
    "links": [
      {
        "target": "3593b445-773a-469e-977f-0456e4224d1c",
        "type": "CAUSE"
      }
    ],
    "meta": {
      "time": 1533633124259,
      "source": {
        "domainId": "example.domain"
      },
      "id": "9aa39ad1-d4a0-4caf-a675-502d82fc295e",
      "type": "EiffelActivityTriggeredEvent",
      "version": "1.0.0"
    },
    "data": {
      "triggers": [
        {
          "type": "EIFFEL_EVENT"
        }
      ],
      "customData": [
        {
          "key": "name",
          "value": "ActT3"
        },
        {
          "key": "iteration",
          "value": 1
        }
      ],
      "categories": [
        "Sub-system Test Activity"
      ],
      "executionType": "AUTOMATED",
      "name": "Act3"
    }
  },
  {
    "links": [
      {
        "target": "9aa39ad1-d4a0-4caf-a675-502d82fc295e",
        "type": "ACTIVITY_EXECUTION"
      }
    ],
    "meta": {
      "time": 1533633124262,
      "source": {
        "domainId": "example.domain"
      },
      "id": "bc7d7b52-866f-4c0d-9e62-f635607ac248",
      "type": "EiffelActivityStartedEvent",
      "version": "1.0.0"
    },
    "data": {
      "customData": [
        {
          "key": "name",
          "value": "ActS3"
        },
        {
          "key": "iteration",
          "value": 1
        }
      ]
    }
  },
  {
    "links": [
      {
        "target": "9aa39ad1-d4a0-4caf-a675-502d82fc295e",
        "type": "CONTEXT"
      }
    ],
    "meta": {
      "time": 1533633126262,
      "source": {
        "domainId": "example.domain"
      },
      "id": "20a470bc-70ae-4ce8-b6a2-1480f43d2f7f",
      "type": "EiffelTestSuiteStartedEvent",
      "version": "1.0.0"
    },
    "data": {
      "customData": [
        {
          "key": "name",
          "value": "TSS1"
        },
        {
          "key": "iteration",
          "value": 1
        }
      ],
      "categories": [
        "Pre system integration tests"
      ],
      "name": "My functional test suite",
      "types": [
        "FUNCTIONAL"
      ]
    }
  },
  {
    "links": [
      {
        "target": "20a470bc-70ae-4ce8-b6a2-1480f43d2f7f",
        "type": "CONTEXT"
      },
      {
        "target": "208cfc27-23f7-469d-a741-b15ac150bf8c",
        "type": "IUT"
      }
    ],
    "meta": {
      "time": 1533633126362,
      "source": {
        "domainId": "example.domain"
      },
      "id": "16d9350f-482e-4b51-aceb-f9f3ad662bd7",
      "type": "EiffelTestCaseTriggeredEvent",
      "version": "1.0.0"
    },
    "data": {
      "customData": [
        {
          "key": "name",
          "value": "TCT5"
        },
        {
          "key": "iteration",
          "value": 1
        }
      ],
      "testCase": {
        "id": "TC5",
        "uri": "https://other-tm.company.com/testCase/TC5",
        "tracker": "My Other Test Management System"
      }
    }
  },
  {
    "links": [
      {
        "target": "20a470bc-70ae-4ce8-b6a2-1480f43d2f7f",
        "type": "CONTEXT"
      },
      {
        "target": "208cfc27-23f7-469d-a741-b15ac150bf8c",
        "type": "IUT"
      }
    ],
    "meta": {
      "time": 1533633126363,
      "source": {
        "domainId": "example.domain"
      },
      "id": "fb634111-7d1d-4143-a9c6-1b4a26f8503b",
      "type": "EiffelTestCaseTriggeredEvent",
      "version": "1.0.0"
    },
    "data": {
      "customData": [
        {
          "key": "name",
          "value": "TCT6"
        },
        {
          "key": "iteration",
          "value": 1
        }
      ],
      "testCase": {
        "id": "TC6",
        "uri": "https://other-tm.company.com/testCase/TC6",
        "tracker": "My Other Test Management System"
      }
    }
  },
  {
    "links": [
      {
        "target": "20a470bc-70ae-4ce8-b6a2-1480f43d2f7f",
        "type": "CONTEXT"
      },
      {
        "target": "208cfc27-23f7-469d-a741-b15ac150bf8c",
        "type": "IUT"
      }
    ],
    "meta": {
      "time": 1533633126364,
      "source": {
        "domainId": "example.domain"
      },
      "id": "88f11a6c-7e64-4a1a-ae85-019e8092107e",
      "type": "EiffelTestCaseTriggeredEvent",
      "version": "1.0.0"
    },
    "data": {
      "customData": [
        {
          "key": "name",
          "value": "TCT7"
        },
        {
          "key": "iteration",
          "value": 1
        }
      ],
      "testCase": {
        "id": "TC6",
        "uri": "https://other-tm.company.com/testCase/TC6",
        "tracker": "My Other Test Management System"
      }
    }
  },
  {
    "links": [
      {
        "target": "16d9350f-482e-4b51-aceb-f9f3ad662bd7",
        "type": "TEST_CASE_EXECUTION"
      }
    ],
    "meta": {
      "time": 1533633126365,
      "source": {
        "domainId": "example.domain"
      },
      "id": "324eecf6-0865-4adc-9cac-7f53f9c8cfbd",
      "type": "EiffelTestCaseStartedEvent",
      "version": "1.0.0"
    },
    "data": {
      "customData": [
        {
          "key": "name",
          "value": "TCS5"
        },
        {
          "key": "iteration",
          "value": 1
        }
      ]
    }
  },
  {
    "links": [
      {
        "target": "fb634111-7d1d-4143-a9c6-1b4a26f8503b",
        "type": "TEST_CASE_EXECUTION"
      }
    ],
    "meta": {
      "time": 1533633126367,
      "source": {
        "domainId": "example.domain"
      },
      "id": "345eaded-44bb-4020-ab68-d176a04f31f0",
      "type": "EiffelTestCaseStartedEvent",
      "version": "1.0.0"
    },
    "data": {
      "customData": [
        {
          "key": "name",
          "value": "TCS6"
        },
        {
          "key": "iteration",
          "value": 1
        }
      ]
    }
  },
  {
    "links": [
      {
        "target": "88f11a6c-7e64-4a1a-ae85-019e8092107e",
        "type": "TEST_CASE_EXECUTION"
      }
    ],
    "meta": {
      "time": 1533633126368,
      "source": {
        "domainId": "example.domain"
      },
      "id": "88042f00-d7b9-4215-a1c7-82ae14477170",
      "type": "EiffelTestCaseStartedEvent",
      "version": "1.0.0"
    },
    "data": {
      "customData": [
        {
          "key": "name",
          "value": "TCS7"
        },
        {
          "key": "iteration",
          "value": 1
        }
      ]
    }
  },
  {
    "links": [
      {
        "target": "16d9350f-482e-4b51-aceb-f9f3ad662bd7",
        "type": "TEST_CASE_EXECUTION"
      }
    ],
    "meta": {
      "time": 1533633136368,
      "source": {
        "domainId": "example.domain"
      },
      "id": "029925ca-bae7-49ea-8721-0a71837b0c80",
      "type": "EiffelTestCaseFinishedEvent",
      "version": "1.0.0"
    },
    "data": {
      "outcome": {
        "conclusion": "SUCCESSFUL",
        "verdict": "PASSED"
      },
      "customData": [
        {
          "key": "name",
          "value": "TCF5"
        },
        {
          "key": "iteration",
          "value": 1
        }
      ]
    }
  },
  {
    "links": [
      {
        "target": "fb634111-7d1d-4143-a9c6-1b4a26f8503b",
        "type": "TEST_CASE_EXECUTION"
      }
    ],
    "meta": {
      "time": 1533633139368,
      "source": {
        "domainId": "example.domain"
      },
      "id": "7677fd1e-040a-4fa4-9f57-92146a490427",
      "type": "EiffelTestCaseFinishedEvent",
      "version": "1.0.0"
    },
    "data": {
      "outcome": {
        "conclusion": "SUCCESSFUL",
        "verdict": "PASSED"
      },
      "customData": [
        {
          "key": "name",
          "value": "TCF6"
        },
        {
          "key": "iteration",
          "value": 1
        }
      ]
    }
  },
  {
    "links": [
      {
        "target": "88f11a6c-7e64-4a1a-ae85-019e8092107e",
        "type": "TEST_CASE_EXECUTION"
      }
    ],
    "meta": {
      "time": 1533633144368,
      "source": {
        "domainId": "example.domain"
      },
      "id": "c4f3a6ee-3e86-45d0-99a2-bfe985765958",
      "type": "EiffelTestCaseFinishedEvent",
      "version": "1.0.0"
    },
    "data": {
      "outcome": {
        "conclusion": "SUCCESSFUL",
        "verdict": "PASSED"
      },
      "customData": [
        {
          "key": "name",
          "value": "TCF7"
        },
        {
          "key": "iteration",
          "value": 1
        }
      ]
    }
  },
  {
    "links": [
      {
        "target": "20a470bc-70ae-4ce8-b6a2-1480f43d2f7f",
        "type": "TEST_SUITE_EXECUTION"
      }
    ],
    "meta": {
      "time": 1533633144418,
      "source": {
        "domainId": "example.domain"
      },
      "id": "31ad7612-aa5c-4736-a98d-6500f0d4ce1a",
      "type": "EiffelTestSuiteFinishedEvent",
      "version": "1.0.0"
    },
    "data": {
      "outcome": {
        "verdict": "PASSED"
      },
      "customData": [
        {
          "key": "name",
          "value": "TSF1"
        },
        {
          "key": "iteration",
          "value": 1
        }
      ]
    }
  },
  {
    "links": [
      {
        "target": "9aa39ad1-d4a0-4caf-a675-502d82fc295e",
        "type": "ACTIVITY_EXECUTION"
      }
    ],
    "meta": {
      "time": 1533633144421,
      "source": {
        "domainId": "example.domain"
      },
      "id": "42132f28-5987-45a7-9fbb-0863250758ef",
      "type": "EiffelActivityFinishedEvent",
      "version": "1.0.0"
    },
    "data": {
      "outcome": {
        "conclusion": "SUCCESSFUL"
      },
      "customData": [
        {
          "key": "name",
          "value": "ActF3"
        },
        {
          "key": "iteration",
          "value": 1
        }
      ]
    }
  },
  {
    "links": [
      {
        "target": "31ad7612-aa5c-4736-a98d-6500f0d4ce1a",
        "type": "CAUSE"
      },
      {
        "target": "208cfc27-23f7-469d-a741-b15ac150bf8c",
        "type": "SUBJECT"
      }
    ],
    "meta": {
      "time": 1533633144721,
      "source": {
        "domainId": "example.domain"
      },
      "id": "68159775-c3e5-4613-b6ac-f471aac96083",
      "type": "EiffelConfidenceLevelModifiedEvent",
      "version": "1.0.0"
    },
    "data": {
      "customData": [
        {
          "key": "name",
          "value": "CLM2"
        },
        {
          "key": "iteration",
          "value": 1
        }
      ],
      "value": "SUCCESS",
      "name": "readyForSystemIntegration"
    }
  },
  {
    "links": [
      {
        "target": "68159775-c3e5-4613-b6ac-f471aac96083",
        "type": "CAUSE"
      },
      {
        "target": "208cfc27-23f7-469d-a741-b15ac150bf8c",
        "type": "ELEMENT"
      },
      {
        "target": "a3a48338-35c7-426b-9cc3-42ffbf19881c",
        "type": "ELEMENT"
      }
    ],
    "meta": {
      "time": 1533633145021,
      "source": {
        "domainId": "example.domain"
      },
      "id": "d6683047-7d42-4d2b-b601-a5473e51479d",
      "type": "EiffelCompositionDefinedEvent",
      "version": "1.0.0"
    },
    "data": {
      "customData": [
        {
          "key": "name",
          "value": "CDef1"
        },
        {
          "key": "iteration",
          "value": 1
        }
      ],
      "name": "Composition 1",
      "version": "1"
    }
  },
  {
    "links": [
      {
        "target": "d6683047-7d42-4d2b-b601-a5473e51479d",
        "type": "COMPOSITION"
      },
      {
        "target": "38c7d1d5-3f62-4932-94a7-f7be7b5200e6",
        "type": "ENVIRONMENT"
      },
      {
        "target": "d6683047-7d42-4d2b-b601-a5473e51479d",
        "type": "CAUSE"
      }
    ],
    "meta": {
      "time": 1533633146021,
      "source": {
        "domainId": "example.domain"
      },
      "id": "2026ebe0-6ce6-4ce2-a687-557832aad1d9",
      "type": "EiffelArtifactCreatedEvent",
      "version": "2.0.0"
    },
    "data": {
      "customData": [
        {
          "key": "name",
          "value": "ArtC1"
        },
        {
          "key": "iteration",
          "value": 1
        }
      ],
      "identity": "pkg:maven/com.mycompany.myproduct/complete-system@1.1.0"
    }
  },
  {
    "links": [
      {
        "target": "2026ebe0-6ce6-4ce2-a687-557832aad1d9",
        "type": "ARTIFACT"
      },
      {
        "target": "2026ebe0-6ce6-4ce2-a687-557832aad1d9",
        "type": "CAUSE"
      }
    ],
    "meta": {
      "time": 1533633147021,
      "source": {
        "domainId": "example.domain"
      },
      "id": "0c952030-1741-4723-89f5-6bc0f1b4b155",
      "type": "EiffelArtifactPublishedEvent",
      "version": "1.0.0"
    },
    "data": {
      "locations": [
        {
          "uri": "https://myrepository.com/myCompleteSystemArtifact",
          "type": "PLAIN"
        }
      ],
      "customData": [
        {
          "key": "name",
          "value": "ArtP1"
        },
        {
          "key": "iteration",
          "value": 1
        }
      ]
    }
  },
  {
    "links": [
      {
        "target": "0c952030-1741-4723-89f5-6bc0f1b4b155",
        "type": "CAUSE"
      }
    ],
    "meta": {
      "time": 1533633148021,
      "source": {
        "domainId": "example.domain"
      },
      "id": "82e31f53-3641-4fee-96d1-4262b91d838a",
      "type": "EiffelActivityTriggeredEvent",
      "version": "1.0.0"
    },
    "data": {
      "triggers": [
        {
          "type": "EIFFEL_EVENT"
        }
      ],
      "customData": [
        {
          "key": "name",
          "value": "ActT1"
        },
        {
          "key": "iteration",
          "value": 1
        }
      ],
      "categories": [
        "Test Activity"
      ],
      "executionType": "AUTOMATED",
      "name": "Act1"
    }
  },
  {
    "links": [
      {
        "target": "82e31f53-3641-4fee-96d1-4262b91d838a",
        "type": "ACTIVITY_EXECUTION"
      }
    ],
    "meta": {
      "time": 1533633148023,
      "source": {
        "domainId": "example.domain"
      },
      "id": "f0c26197-48ef-400c-a4c7-101aa74fd171",
      "type": "EiffelActivityStartedEvent",
      "version": "1.0.0"
    },
    "data": {
      "customData": [
        {
          "key": "name",
          "value": "ActS1"
        },
        {
          "key": "iteration",
          "value": 1
        }
      ]
    }
  },
  {
    "links": [
      {
        "target": "0c952030-1741-4723-89f5-6bc0f1b4b155",
        "type": "CAUSE"
      }
    ],
    "meta": {
      "time": 1533633148073,
      "source": {
        "domainId": "example.domain"
      },
      "id": "f27398b9-dfa6-49c5-994f-439b12473702",
      "type": "EiffelActivityTriggeredEvent",
      "version": "1.0.0"
    },
    "data": {
      "triggers": [
        {
          "type": "EIFFEL_EVENT"
        }
      ],
      "customData": [
        {
          "key": "name",
          "value": "ActT2"
        },
        {
          "key": "iteration",
          "value": 1
        }
      ],
      "categories": [
        "Test Activity"
      ],
      "executionType": "AUTOMATED",
      "name": "Act2"
    }
  },
  {
    "links": [
      {
        "target": "82e31f53-3641-4fee-96d1-4262b91d838a",
        "type": "CONTEXT"
      },
      {
        "target": "2026ebe0-6ce6-4ce2-a687-557832aad1d9",
        "type": "IUT"
      }
    ],
    "meta": {
      "time": 1533633148074,
      "source": {
        "domainId": "example.domain"
      },
      "id": "a02f748b-e4e2-4504-903d-f1ab6e07c0b0",
      "type": "EiffelTestCaseTriggeredEvent",
      "version": "1.0.0"
    },
    "data": {
      "customData": [
        {
          "key": "name",
          "value": "TCT1"
        },
        {
          "key": "iteration",
          "value": 1
        }
      ],
      "testCase": {
        "id": "TC1",
        "uri": "http://tm.company.com/browse/TC1",
        "tracker": "My First Test Management System"
      }
    }
  },
  {
    "links": [
      {
        "target": "82e31f53-3641-4fee-96d1-4262b91d838a",
        "type": "CONTEXT"
      },
      {
        "target": "2026ebe0-6ce6-4ce2-a687-557832aad1d9",
        "type": "IUT"
      }
    ],
    "meta": {
      "time": 1533633148075,
      "source": {
        "domainId": "example.domain"
      },
      "id": "4cdc56c9-28df-4c6a-8c10-022af9128802",
      "type": "EiffelTestCaseTriggeredEvent",
      "version": "1.0.0"
    },
    "data": {
      "customData": [
        {
          "key": "name",
          "value": "TCT2"
        },
        {
          "key": "iteration",
          "value": 1
        }
      ],
      "testCase": {
        "id": "TC2",
        "uri": "http://tm.company.com/browse/TC2",
        "tracker": "My First Test Management System"
      }
    }
  },
  {
    "links": [
      {
        "target": "a02f748b-e4e2-4504-903d-f1ab6e07c0b0",
        "type": "TEST_CASE_EXECUTION"
      }
    ],
    "meta": {
      "time": 1533633149075,
      "source": {
        "domainId": "example.domain"
      },
      "id": "9f249fc0-b7c7-4e18-9d55-801fd9156952",
      "type": "EiffelTestCaseStartedEvent",
      "version": "1.0.0"
    },
    "data": {
      "customData": [
        {
          "key": "name",
          "value": "TCS1"
        },
        {
          "key": "iteration",
          "value": 1
        }
      ]
    }
  },
  {
    "links": [
      {
        "target": "4cdc56c9-28df-4c6a-8c10-022af9128802",
        "type": "TEST_CASE_EXECUTION"
      }
    ],
    "meta": {
      "time": 1533633149175,
      "source": {
        "domainId": "example.domain"
      },
      "id": "26fd9ebd-9a14-4e60-a39f-81edf8820fd1",
      "type": "EiffelTestCaseStartedEvent",
      "version": "1.0.0"
    },
    "data": {
      "customData": [
        {
          "key": "name",
          "value": "TCS2"
        },
        {
          "key": "iteration",
          "value": 1
        }
      ]
    }
  },
  {
    "links": [
      {
        "target": "4cdc56c9-28df-4c6a-8c10-022af9128802",
        "type": "TEST_CASE_EXECUTION"
      }
    ],
    "meta": {
      "time": 1533633199175,
      "source": {
        "domainId": "example.domain"
      },
      "id": "e9e2aa26-783a-4f44-91f4-8721e8f67587",
      "type": "EiffelTestCaseFinishedEvent",
      "version": "1.0.0"
    },
    "data": {
      "outcome": {
        "conclusion": "SUCCESSFUL",
        "verdict": "PASSED"
      },
      "customData": [
        {
          "key": "name",
          "value": "TCF2"
        },
        {
          "key": "iteration",
          "value": 1
        }
      ]
    }
  },
  {
    "links": [
      {
        "target": "a02f748b-e4e2-4504-903d-f1ab6e07c0b0",
        "type": "TEST_CASE_EXECUTION"
      }
    ],
    "meta": {
      "time": 1533633202175,
      "source": {
        "domainId": "example.domain"
      },
      "id": "28172f76-9b8f-4ace-b37d-809ddd62e375",
      "type": "EiffelTestCaseFinishedEvent",
      "version": "1.0.0"
    },
    "data": {
      "outcome": {
        "conclusion": "SUCCESSFUL",
        "verdict": "PASSED"
      },
      "customData": [
        {
          "key": "name",
          "value": "TCF1"
        },
        {
          "key": "iteration",
          "value": 1
        }
      ]
    }
  },
  {
    "links": [
      {
        "target": "82e31f53-3641-4fee-96d1-4262b91d838a",
        "type": "ACTIVITY_EXECUTION"
      }
    ],
    "meta": {
      "time": 1533633202275,
      "source": {
        "domainId": "example.domain"
      },
      "id": "d3c274e0-1c42-4871-83c3-a585e0f5fe9c",
      "type": "EiffelActivityFinishedEvent",
      "version": "1.0.0"
    },
    "data": {
      "outcome": {
        "conclusion": "SUCCESSFUL"
      },
      "customData": [
        {
          "key": "name",
          "value": "ActF1"
        },
        {
          "key": "iteration",
          "value": 1
        }
      ]
    }
  },
  {
    "links": [
      {
        "target": "f27398b9-dfa6-49c5-994f-439b12473702",
        "type": "ACTIVITY_EXECUTION"
      }
    ],
    "meta": {
      "time": 1533633302275,
      "source": {
        "domainId": "example.domain"
      },
      "id": "220f9fa3-3d9f-46af-bd5f-2c61b41f2712",
      "type": "EiffelActivityStartedEvent",
      "version": "1.0.0"
    },
    "data": {
      "customData": [
        {
          "key": "name",
          "value": "ActS2"
        },
        {
          "key": "iteration",
          "value": 1
        }
      ]
    }
  },
  {
    "links": [
      {
        "target": "f27398b9-dfa6-49c5-994f-439b12473702",
        "type": "CONTEXT"
      },
      {
        "target": "2026ebe0-6ce6-4ce2-a687-557832aad1d9",
        "type": "IUT"
      }
    ],
    "meta": {
      "time": 1533633302276,
      "source": {
        "domainId": "example.domain"
      },
      "id": "2177c1a2-4086-438d-bf76-a9026d121461",
      "type": "EiffelTestCaseTriggeredEvent",
      "version": "1.0.0"
    },
    "data": {
      "customData": [
        {
          "key": "name",
          "value": "TCT3"
        },
        {
          "key": "iteration",
          "value": 1
        }
      ],
      "testCase": {
        "id": "TC3",
        "uri": "http://tm.company.com/browse/TC3",
        "tracker": "My First Test Management System"
      }
    }
  },
  {
    "links": [
      {
        "target": "2177c1a2-4086-438d-bf76-a9026d121461",
        "type": "TEST_CASE_EXECUTION"
      }
    ],
    "meta": {
      "time": 1533633302476,
      "source": {
        "domainId": "example.domain"
      },
      "id": "1c70eaf4-d035-496d-a509-ee7b52c7044d",
      "type": "EiffelTestCaseStartedEvent",
      "version": "1.0.0"
    },
    "data": {
      "customData": [
        {
          "key": "name",
          "value": "TCS3"
        },
        {
          "key": "iteration",
          "value": 1
        }
      ]
    }
  },
  {
    "links": [
      {
        "target": "2177c1a2-4086-438d-bf76-a9026d121461",
        "type": "TEST_CASE_EXECUTION"
      }
    ],
    "meta": {
      "time": 1533633312476,
      "source": {
        "domainId": "example.domain"
      },
      "id": "8e0a20cf-19ca-4521-83e5-b65b4bbc92e6",
      "type": "EiffelTestCaseFinishedEvent",
      "version": "1.0.0"
    },
    "data": {
      "outcome": {
        "conclusion": "SUCCESSFUL",
        "verdict": "PASSED"
      },
      "customData": [
        {
          "key": "name",
          "value": "TCF3"
        },
        {
          "key": "iteration",
          "value": 1
        }
      ]
    }
  },
  {
    "links": [
      {
        "target": "f27398b9-dfa6-49c5-994f-439b12473702",
        "type": "CONTEXT"
      },
      {
        "target": "2026ebe0-6ce6-4ce2-a687-557832aad1d9",
        "type": "IUT"
      }
    ],
    "meta": {
      "time": 1533633312477,
      "source": {
        "domainId": "example.domain"
      },
      "id": "55b29ff8-bf00-4477-aa3e-6619264198d4",
      "type": "EiffelTestCaseTriggeredEvent",
      "version": "1.0.0"
    },
    "data": {
      "customData": [
        {
          "key": "name",
          "value": "TCT4"
        },
        {
          "key": "iteration",
          "value": 1
        }
      ],
      "testCase": {
        "id": "TC4",
        "uri": "http://tm.company.com/browse/TC4",
        "tracker": "My First Test Management System"
      }
    }
  },
  {
    "links": [
      {
        "target": "55b29ff8-bf00-4477-aa3e-6619264198d4",
        "type": "TEST_CASE_EXECUTION"
      }
    ],
    "meta": {
      "time": 1533633312577,
      "source": {
        "domainId": "example.domain"
      },
      "id": "e4a41dec-bd52-4284-945c-440c5ba83c32",
      "type": "EiffelTestCaseStartedEvent",
      "version": "1.0.0"
    },
    "data": {
      "customData": [
        {
          "key": "name",
          "value": "TCS4"
        },
        {
          "key": "iteration",
          "value": 1
        }
      ]
    }
  },
  {
    "links": [
      {
        "target": "55b29ff8-bf00-4477-aa3e-6619264198d4",
        "type": "TEST_CASE_EXECUTION"
      }
    ],
    "meta": {
      "time": 1533633432577,
      "source": {
        "domainId": "example.domain"
      },
      "id": "bcc8940c-237c-416e-a9b5-07cfb26d045a",
      "type": "EiffelTestCaseFinishedEvent",
      "version": "1.0.0"
    },
    "data": {
      "outcome": {
        "conclusion": "SUCCESSFUL",
        "verdict": "PASSED"
      },
      "customData": [
        {
          "key": "name",
          "value": "TCF4"
        },
        {
          "key": "iteration",
          "value": 1
        }
      ]
    }
  },
  {
    "links": [
      {
        "target": "f27398b9-dfa6-49c5-994f-439b12473702",
        "type": "ACTIVITY_EXECUTION"
      }
    ],
    "meta": {
      "time": 1533633432597,
      "source": {
        "domainId": "example.domain"
      },
      "id": "52c90dc5-6729-47e5-874e-4aa0464ec857",
      "type": "EiffelActivityFinishedEvent",
      "version": "1.0.0"
    },
    "data": {
      "outcome": {
        "conclusion": "SUCCESSFUL"
      },
      "customData": [
        {
          "key": "name",
          "value": "ActF2"
        },
        {
          "key": "iteration",
          "value": 1
        }
      ]
    }
  },
  {
    "links": [
      {
        "target": "2026ebe0-6ce6-4ce2-a687-557832aad1d9",
        "type": "SUBJECT"
      },
      {
        "target": "28172f76-9b8f-4ace-b37d-809ddd62e375",
        "type": "CAUSE"
      },
      {
        "target": "e9e2aa26-783a-4f44-91f4-8721e8f67587",
        "type": "CAUSE"
      },
      {
        "target": "8e0a20cf-19ca-4521-83e5-b65b4bbc92e6",
        "type": "CAUSE"
      },
      {
        "target": "bcc8940c-237c-416e-a9b5-07cfb26d045a",
        "type": "CAUSE"
      }
    ],
    "meta": {
      "time": 1533633435097,
      "source": {
        "domainId": "example.domain"
      },
      "id": "748b3e16-8f02-4316-9b35-f0d83d11e218",
      "type": "EiffelConfidenceLevelModifiedEvent",
      "version": "1.0.0"
    },
    "data": {
      "customData": [
        {
          "key": "name",
          "value": "CLM1"
        },
        {
          "key": "iteration",
          "value": 1
        }
      ],
      "value": "SUCCESS",
      "name": "readyForRelease"
    }
  }
]
