{
  "meta": {
    "type": "EiffelArtifactCreatedEvent",
    "version": "3.0.0",
    "time": 1234567890,
    "id": "aaaaaaaa-bbbb-5ccc-8ddd-eeeeeeeeeee0",
    "source": {
      "serializer": "pkg:maven/com.mycompany.tools/eiffel-serializer@1.0.3"
    },
    "tags": [
      "fast-track",
      "customer-a"
    ]
  },
  "data": {
    "identity": "pkg:maven/com.mycompany.myproduct/artifact-name@2.1.7",
    "fileInformation": [
      {
        "name": "debug/launch",
        "tags": [
          "debug",
          "launcher"
        ]
      },
      {
        "name": "test/log.txt"
      },
      {
        "name": "bin/launch",
        "tags": [
          "launcher"
        ]
      }
    ],
    "buildCommand": "/my/build/command with arguments",
    "name": "Full verbose artifact name"
  },
  "links": [
    {
      "type": "CAUSE",
      "target": "aaaaaaaa-bbbb-5ccc-8ddd-eeeeeeeeeee1"
    },
    {
      "type": "PREVIOUS_VERSION",
      "target": "aaaaaaaa-bbbb-5ccc-8ddd-eeeeeeeeeee2"
    },
    {
      "type": "COMPOSITION",
      "target": "aaaaaaaa-bbbb-5ccc-8ddd-eeeeeeeeeee1"
    },
    {
      "type": "ENVIRONMENT",
      "target": "aaaaaaaa-bbbb-5ccc-8ddd-eeeeeeeeeee3"
    }
  ]
}
